{"_invocation_id": "bc32b9ae-3b2b-4855-a323-94e69826ed7d", "linked": {"0": {"name": "source.passportcard_travel.bronze.mrr_agents", "type": "source", "succ": [20]}, "1": {"name": "source.passportcard_travel.bronze.mrr_dc_pod_agreements", "type": "source", "succ": [22]}, "2": {"name": "source.passportcard_travel.bronze.mrr_app_policy_benefit", "type": "source", "succ": [34]}, "3": {"name": "source.passportcard_travel.bronze.mrr_app_policy_benefit_types", "type": "source", "succ": [35]}, "4": {"name": "source.passportcard_travel.bronze.mrr_app_policy", "type": "source", "succ": [45]}, "5": {"name": "source.passportcard_travel.bronze.mrr_app_policy_coverage", "type": "source", "succ": [37]}, "6": {"name": "source.passportcard_travel.bronze.mrr_app_policy_discount", "type": "source", "succ": [44]}, "7": {"name": "source.passportcard_travel.bronze.mrr_uw_exclusion_codes", "type": "source", "succ": [41]}, "8": {"name": "source.passportcard_travel.bronze.mrr_app_policy_status", "type": "source", "succ": [18]}, "9": {"name": "source.passportcard_travel.bronze.mrr_app_policy_groups", "type": "source", "succ": [31]}, "10": {"name": "source.passportcard_travel.bronze.mrr_app_policy_types", "type": "source", "succ": [27]}, "11": {"name": "source.passportcard_travel.bronze.mrr_app_policy_types_main", "type": "source", "succ": [28]}, "12": {"name": "source.passportcard_travel.bronze.mrr_masterentity", "type": "source", "succ": [29]}, "13": {"name": "source.passportcard_travel.bronze.mrr_app_policy_product_types", "type": "source", "succ": [32]}, "14": {"name": "source.passportcard_travel.bronze.mrr_app_policy_service_types", "type": "source", "succ": [24]}, "15": {"name": "source.passportcard_travel.bronze.mrr_app_policy_service_groups", "type": "source", "succ": [25]}, "16": {"name": "source.passportcard_travel.mng.mng_params", "type": "source", "succ": [21]}, "17": {"name": "model.passportcard_travel.dim_policy_status", "type": "model", "succ": [39, 55, 56]}, "18": {"name": "model.passportcard_travel.stg_bronze__mrr_app_policy_status", "type": "model", "succ": [17]}, "19": {"name": "model.passportcard_travel.dim_agents", "type": "model", "succ": [57, 58, 59, 60]}, "20": {"name": "model.passportcard_travel.stg_bronze__mrr_agents", "type": "model", "succ": [19]}, "21": {"name": "model.passportcard_travel.stg_mng__mng_params", "type": "model", "succ": [19, 26, 38, 39]}, "22": {"name": "model.passportcard_travel.stg_bronze__mrr_dc_pod_agreements", "type": "model", "succ": [19]}, "23": {"name": "model.passportcard_travel.dim_services", "type": "model", "succ": [48, 49]}, "24": {"name": "model.passportcard_travel.stg_bronze_mrr_app_policy_service_types", "type": "model", "succ": [23]}, "25": {"name": "model.passportcard_travel.stg_bronze_mrr_app_policy_service_groups", "type": "model", "succ": [23]}, "26": {"name": "model.passportcard_travel.dim_policy_groups", "type": "model", "succ": [36, 39, 42, 50, 51, 69]}, "27": {"name": "model.passportcard_travel.stg_bronze__mrr_app_policy_types", "type": "model", "succ": [26]}, "28": {"name": "model.passportcard_travel.stg_bronze__mrr_app_policy_types_main", "type": "model", "succ": [26]}, "29": {"name": "model.passportcard_travel.stg_bronze__mrr_masterentity", "type": "model", "succ": [26]}, "30": {"name": "model.passportcard_travel.dim_policy_product_types", "type": "model", "succ": [26, 46, 47]}, "31": {"name": "model.passportcard_travel.stg_bronze__mrr_app_policy_groups", "type": "model", "succ": [26]}, "32": {"name": "model.passportcard_travel.stg_bronze__mrr_app_policy_product_types", "type": "model", "succ": [30]}, "33": {"name": "model.passportcard_travel.dim_benefits", "type": "model", "succ": [39, 52, 53, 54]}, "34": {"name": "model.passportcard_travel.stg_bronze__mrr_app_policy_benefit", "type": "model", "succ": [33]}, "35": {"name": "model.passportcard_travel.stg_bronze__mrr_app_policy_benefit_types", "type": "model", "succ": [33, 54]}, "36": {"name": "model.passportcard_travel.fact_policy_coverage", "type": "model", "succ": [39, 43, 70, 71]}, "37": {"name": "model.passportcard_travel.stg_bronze__mrr_app_policy_coverage", "type": "model", "succ": [36]}, "38": {"name": "model.passportcard_travel.agg_premium_by_member", "type": "model", "succ": [65, 66]}, "39": {"name": "model.passportcard_travel.fact_premiums", "type": "model", "succ": [38, 61, 62]}, "40": {"name": "model.passportcard_travel.fact_uw_exclusion_codes", "type": "model", "succ": [39, 63, 64]}, "41": {"name": "model.passportcard_travel.stg_bronze__mrr_uw_exclusion_codes", "type": "model", "succ": [40]}, "42": {"name": "model.passportcard_travel.fact_policies", "type": "model", "succ": [39, 67, 68, 69]}, "43": {"name": "model.passportcard_travel.fact_policy_discount", "type": "model", "succ": [39, 72, 73]}, "44": {"name": "model.passportcard_travel.stg_bronze__mrr_app_policy_discount", "type": "model", "succ": [43]}, "45": {"name": "model.passportcard_travel.stg_bronze__mrr_app_policy", "type": "model", "succ": [42]}, "46": {"name": "test.passportcard_travel.not_null_dim_policy_product_types_App_Policy_Product_TypesID.1e903e4cdb", "type": "test"}, "47": {"name": "test.passportcard_travel.unique_dim_policy_product_types_App_Policy_Product_TypesID.e6bca4925d", "type": "test"}, "48": {"name": "test.passportcard_travel.not_null_dim_services_serviceid.c1944d0b78", "type": "test"}, "49": {"name": "test.passportcard_travel.unique_dim_services_serviceid.5ae6d79864", "type": "test"}, "50": {"name": "test.passportcard_travel.unique_dim_policy_groups_IdPolicy.933b083935", "type": "test"}, "51": {"name": "test.passportcard_travel.not_null_dim_policy_groups_IdPolicy.0333bf0d19", "type": "test"}, "52": {"name": "test.passportcard_travel.not_null_dim_benefits_benefitid.1af0793f0c", "type": "test"}, "53": {"name": "test.passportcard_travel.unique_dim_benefits_benefitid.84e09c8dcc", "type": "test"}, "54": {"name": "test.passportcard_travel.relationships_dim_benefits_benefittypeid__benefittypeid__ref_stg_bronze__mrr_app_policy_benefit_types_.bc242c94c8", "type": "test"}, "55": {"name": "test.passportcard_travel.not_null_dim_policy_status_StatusID.24380c853c", "type": "test"}, "56": {"name": "test.passportcard_travel.unique_dim_policy_status_StatusID.73712bbf65", "type": "test"}, "57": {"name": "test.passportcard_travel.unique_dim_agents_agentid.6b58e5ff25", "type": "test"}, "58": {"name": "test.passportcard_travel.not_null_dim_agents_agentid.042256bf06", "type": "test"}, "59": {"name": "test.passportcard_travel.accepted_values_dim_agents_not_real_agent__0__1.c81bd96e65", "type": "test"}, "60": {"name": "test.passportcard_travel.accepted_values_dim_agents_is_natbag__0__1.e5b8f34ede", "type": "test"}, "61": {"name": "test.passportcard_travel.not_null_fact_premiums_CoverageId.752737c1aa", "type": "test"}, "62": {"name": "test.passportcard_travel.unique_fact_premiums_CoverageId.2bc422d3f4", "type": "test"}, "63": {"name": "test.passportcard_travel.not_null_fact_uw_exclusion_codes_ExclusionCodeId.abfdd954a8", "type": "test"}, "64": {"name": "test.passportcard_travel.unique_fact_uw_exclusion_codes_ExclusionCodeId.05cc715057", "type": "test"}, "65": {"name": "test.passportcard_travel.not_null_agg_premium_by_member_PolicyID.cd160df4d3", "type": "test"}, "66": {"name": "test.passportcard_travel.unique_agg_premium_by_member_PolicyID.461c02ea70", "type": "test"}, "67": {"name": "test.passportcard_travel.not_null_fact_policies_PolicyID.97d2b24a83", "type": "test"}, "68": {"name": "test.passportcard_travel.unique_fact_policies_PolicyID.c4cbd07d7a", "type": "test"}, "69": {"name": "test.passportcard_travel.relationships_fact_policies_IdPolicy__IdPolicy__ref_dim_policy_groups_.d32aa23908", "type": "test"}, "70": {"name": "test.passportcard_travel.not_null_fact_policy_coverage_CoverageId.c8d4d860a1", "type": "test"}, "71": {"name": "test.passportcard_travel.unique_fact_policy_coverage_CoverageId.e589cfeed9", "type": "test"}, "72": {"name": "test.passportcard_travel.not_null_fact_policy_discount_DiscountId.029aaaf46b", "type": "test"}, "73": {"name": "test.passportcard_travel.unique_fact_policy_discount_DiscountId.06dc2dcca7", "type": "test"}}}